borsar/__init__.py
borsar/_heatmap.py
borsar/_mne_compat.py
borsar/_vizutils.py
borsar/channels.py
borsar/csd.py
borsar/freq.py
borsar/project.py
borsar/stats.py
borsar/utils.py
borsar/viz.py
borsar/cluster/__init__.py
borsar/cluster/_viz3d.py
borsar/cluster/checks.py
borsar/cluster/label.py
borsar/cluster/label_numba.py
borsar/cluster/obj.py
borsar/cluster/stats.py
borsar/cluster/utils.py
borsar/cluster/viz.py
borsar/cluster/tests/test_cluster.py
borsar/cluster/tests/test_clustering.py
borsar/tests/test_channels.py
borsar/tests/test_csd.py
borsar/tests/test_freq.py
borsar/tests/test_project.py
borsar/tests/test_stats.py
borsar/tests/test_utils.py
borsar/tests/test_viz.py
borsar-0.2.dist-info/LICENSE
borsar-0.2.dist-info/METADATA
borsar-0.2.dist-info/WHEEL
borsar-0.2.dist-info/top_level.txt
borsar-0.2.dist-info/RECORD
