Metadata-Version: 2.1
Name: borsar
Version: 0.2
Summary: tools for electrophysiological analysis, especially cluster-based tests.
Maintainer-email: Mikołaj Magnuski <mmagnuski@swps.edu.pl>
License: BSD-3-Clause
Project-URL: Homepage, https://github.com/mmagnuski/borsar
Keywords: neuroscience,neuroimaging,MEG,EEG,brain
Classifier: Intended Audience :: Science/Research
Classifier: Intended Audience :: Developers
Classifier: License :: OSI Approved
Classifier: Programming Language :: Python
Classifier: Topic :: Software Development
Classifier: Topic :: Scientific/Engineering
Classifier: Operating System :: Microsoft :: Windows
Classifier: Operating System :: POSIX
Classifier: Operating System :: Unix
Classifier: Operating System :: MacOS
Classifier: Programming Language :: Python :: 3
Requires-Python: >=3.8
License-File: LICENSE
Requires-Dist: numpy>=1.15.4
Requires-Dist: scipy>=1.7.1
Requires-Dist: matplotlib>=3.5.0
Requires-Dist: pandas
Requires-Dist: scikit-image
Requires-Dist: mne>=1.0.0
Requires-Dist: tqdm
Requires-Dist: h5io
Requires-Dist: h5py
